ctyunsdk_hpfs20220909/__init__.py
ctyunsdk_hpfs20220909/hpfs_client.py
ctyunsdk_hpfs20220909/models/__init__.py
ctyunsdk_hpfs20220909/models/v4_hpfs_allocable_quota_sfs.py
ctyunsdk_hpfs20220909/models/v4_hpfs_capacity_quota_sfs.py
ctyunsdk_hpfs20220909/models/v4_hpfs_count_quota_sfs.py
ctyunsdk_hpfs20220909/models/v4_hpfs_dataflow_quota_sfs.py
ctyunsdk_hpfs20220909/models/v4_hpfs_delete_dataflow.py
ctyunsdk_hpfs20220909/models/v4_hpfs_delete_fileset.py
ctyunsdk_hpfs20220909/models/v4_hpfs_delete_protocol_service.py
ctyunsdk_hpfs20220909/models/v4_hpfs_info_by_name_sfs.py
ctyunsdk_hpfs20220909/models/v4_hpfs_info_dataflow.py
ctyunsdk_hpfs20220909/models/v4_hpfs_info_dataflowtask.py
ctyunsdk_hpfs20220909/models/v4_hpfs_info_directory.py
ctyunsdk_hpfs20220909/models/v4_hpfs_info_fileset.py
ctyunsdk_hpfs20220909/models/v4_hpfs_info_protocol_service.py
ctyunsdk_hpfs20220909/models/v4_hpfs_info_sfs.py
ctyunsdk_hpfs20220909/models/v4_hpfs_list_baseline.py
ctyunsdk_hpfs20220909/models/v4_hpfs_list_cluster.py
ctyunsdk_hpfs20220909/models/v4_hpfs_list_cluster_by_device.py
ctyunsdk_hpfs20220909/models/v4_hpfs_list_dataflow.py
ctyunsdk_hpfs20220909/models/v4_hpfs_list_dataflowtask.py
ctyunsdk_hpfs20220909/models/v4_hpfs_list_fileset.py
ctyunsdk_hpfs20220909/models/v4_hpfs_list_label_by_sfs.py
ctyunsdk_hpfs20220909/models/v4_hpfs_list_protocol_service.py
ctyunsdk_hpfs20220909/models/v4_hpfs_list_region.py
ctyunsdk_hpfs20220909/models/v4_hpfs_list_sfs.py
ctyunsdk_hpfs20220909/models/v4_hpfs_list_sfs_by_cluster.py
ctyunsdk_hpfs20220909/models/v4_hpfs_list_sfs_by_label.py
ctyunsdk_hpfs20220909/models/v4_hpfs_list_sfs_by_sfstype.py
ctyunsdk_hpfs20220909/models/v4_hpfs_list_zone.py
ctyunsdk_hpfs20220909/models/v4_hpfs_new_dataflow.py
ctyunsdk_hpfs20220909/models/v4_hpfs_new_dataflowtask.py
ctyunsdk_hpfs20220909/models/v4_hpfs_new_directory.py
ctyunsdk_hpfs20220909/models/v4_hpfs_new_fileset.py
ctyunsdk_hpfs20220909/models/v4_hpfs_new_protocol_service.py
ctyunsdk_hpfs20220909-2.0.0.dist-info/licenses/LICENSE.txt
ctyunsdk_hpfs20220909-2.0.0.dist-info/METADATA
ctyunsdk_hpfs20220909-2.0.0.dist-info/WHEEL
ctyunsdk_hpfs20220909-2.0.0.dist-info/top_level.txt
ctyunsdk_hpfs20220909-2.0.0.dist-info/RECORD
